fogg.py
fogg-0.1.dist-info/LICENSE
fogg-0.1.dist-info/WHEEL
fogg-0.1.dist-info/METADATA
fogg-0.1.dist-info/RECORD
