Metadata-Version: 2.1
Name: fogg
Version: 0.1
Summary: fogg: cloud infrastructure
Author-email: defn Nghiem <iam@defn.sh>
Classifier: License :: OSI Approved :: Apache Software License
Project-URL: Home, https://defn.sh/fogg
